tsgenrs/__init__.py
tsgenrs/generators.py
tsgenrs/time_serie.py
tsgenrs-0.1.0.dist-info/METADATA
tsgenrs-0.1.0.dist-info/WHEEL
tsgenrs-0.1.0.dist-info/RECORD
