Metadata-Version: 2.1
Name: tsgenrs
Version: 0.1.0
Summary: 
License: MIT
Author: Ruben Selander
Author-email: 77073569+Reversehobo@users.noreply.github.com
Requires-Python: >=3.9,<4.0
Classifier: License :: OSI Approved :: MIT License
Classifier: Programming Language :: Python :: 3
Classifier: Programming Language :: Python :: 3.9
Classifier: Programming Language :: Python :: 3.10
Classifier: Programming Language :: Python :: 3.11
Classifier: Programming Language :: Python :: 3.12
Requires-Dist: numpy (>=1.26.3,<2.0.0)
Requires-Dist: pandas (>=2.1.4,<3.0.0)
